elm_estimator/__init__.py
elm_estimator/classifier.py
elm_estimator/function.py
elm_estimator/regressor.py
elm_estimator-0.0.1.dist-info/DESCRIPTION.rst
elm_estimator-0.0.1.dist-info/METADATA
elm_estimator-0.0.1.dist-info/RECORD
elm_estimator-0.0.1.dist-info/WHEEL
elm_estimator-0.0.1.dist-info/metadata.json
elm_estimator-0.0.1.dist-info/top_level.txt
