Metadata-Version: 2.0
Name: elm-estimator
Version: 0.0.1
Summary: An Extreme Learning Machine implementaion written in Python.
Home-page: https://github.com/nel215/elm_estimator
Author: nel215
Author-email: otomo.yuhei@gmail.com
License: UNKNOWN
Keywords: machine learning
Platform: UNKNOWN
Classifier: Development Status :: 3 - Alpha
Classifier: Environment :: Console
Classifier: License :: OSI Approved :: Apache Software License
Classifier: Topic :: Scientific/Engineering :: Artificial Intelligence
Requires-Dist: numpy
Requires-Dist: scikit-learn
Requires-Dist: scipy
